[{"x": 37.8694291, "y": -122.2535688, "weight": 2.291666666666667, "name": "Cafe Zeb", "cluster": 0}, {"x": 37.8651779, "y": -122.2586396, "weight": 3.2083333333333335, "name": "Ann's Kitchen", "cluster": 0}, {"x": 37.8752289, "y": -122.2601962, "weight": 3.0, "name": "Northside Cafe", "cluster": 1}, {"x": 37.8695199, "y": -122.2519943, "weight": 3.2083333333333335, "name": "International House Cafe", "cluster": 0}, {"x": 37.8701853, "y": -122.2658691, "weight": 4.125, "name": "The Sunny Side Caf\u00e9", "cluster": 1}, {"x": 37.8680114, "y": -122.2583343, "weight": 3.2083333333333335, "name": "Cafe Durant", "cluster": 0}]